jaxmd_tools/__init__.py
jaxmd_tools/_src/__init__.py
jaxmd_tools/_src/io.py
jaxmd_tools/_src/md.py
jaxmd_tools/_src/types.py
jaxmd_tools/_src/utils.py
jaxmd_tools/io.py
jaxmd_tools/utils.py
jaxmd_tools-0.1.3.dist-info/WHEEL
jaxmd_tools-0.1.3.dist-info/METADATA
jaxmd_tools-0.1.3.dist-info/RECORD
