Metadata-Version: 2.1
Name: jaxmd-tools
Version: 0.1.3
Summary: 
Author: Minjoon Hong
Author-email: mjhong0708@yonsei.ac.kr
Requires-Python: >=3.9,<4.0
Classifier: Programming Language :: Python :: 3
Classifier: Programming Language :: Python :: 3.10
Classifier: Programming Language :: Python :: 3.9
Requires-Dist: ase (>=3.22.1,<4.0.0)
Requires-Dist: jax-md (>=0.1.28,<0.2.0)
Requires-Dist: termcolor (>=1.1.0,<2.0.0)
